CHANGES.txt
CONTRIBUTORS.txt
MANIFEST.in
README.txt
setup.py
docs/LICENSE.txt
src/templer/__init__.py
src/templer.plone.egg-info/PKG-INFO
src/templer.plone.egg-info/SOURCES.txt
src/templer.plone.egg-info/dependency_links.txt
src/templer.plone.egg-info/entry_points.txt
src/templer.plone.egg-info/namespace_packages.txt
src/templer.plone.egg-info/not-zip-safe
src/templer.plone.egg-info/requires.txt
src/templer.plone.egg-info/top_level.txt
src/templer/plone/__init__.py
src/templer/plone/archetype.py
src/templer/plone/plone.py
src/templer/plone/structures.py
src/templer/plone/structures/namespace_profile/src/+namespace_package+/+package+/profiles/default/metadata.xml_tmpl
src/templer/plone/structures/namespace_profile/src/+namespace_package+/+package+/profiles/testing/metadata.xml_tmpl
src/templer/plone/structures/nested_namespace_profile/src/+namespace_package+/+namespace_package2+/+package+/profiles/default/metadata.xml_tmpl
src/templer/plone/structures/nested_namespace_profile/src/+namespace_package+/+namespace_package2+/+package+/profiles/testing/metadata.xml_tmpl
src/templer/plone/templates/archetype/MANIFEST.in_tmpl
src/templer/plone/templates/archetype/setup.py_tmpl
src/templer/plone/templates/archetype/src/+namespace_package+/+package+/README.txt_tmpl
src/templer/plone/templates/archetype/src/+namespace_package+/+package+/__init__.py_tmpl
src/templer/plone/templates/archetype/src/+namespace_package+/+package+/config.py_tmpl
src/templer/plone/templates/archetype/src/+namespace_package+/+package+/configure.zcml_tmpl
src/templer/plone/templates/archetype/src/+namespace_package+/+package+/browser/__init__.py
src/templer/plone/templates/archetype/src/+namespace_package+/+package+/browser/configure.zcml_tmpl
src/templer/plone/templates/archetype/src/+namespace_package+/+package+/content/__init__.py
src/templer/plone/templates/archetype/src/+namespace_package+/+package+/content/configure.zcml_tmpl
src/templer/plone/templates/archetype/src/+namespace_package+/+package+/interfaces/__init__.py
src/templer/plone/templates/archetype/src/+namespace_package+/+package+/portlets/__init__.py
src/templer/plone/templates/archetype/src/+namespace_package+/+package+/portlets/configure.zcml_tmpl
src/templer/plone/templates/archetype/src/+namespace_package+/+package+/profiles/default/factorytool.xml
