Metadata-Version: 1.1
Name: templer.plone
Version: 1.0b3
Summary: Templer system extensions for plone add-on development
Home-page: http://svn.plone.org/svn/collective/templer.plone
Author: Cris Ewing
Author-email: cris@crisewing.com
License: MIT
Keywords: zope buildout plone
Platform: UNKNOWN
Classifier: Development Status :: 4 - Beta
Classifier: Framework :: Zope2
Classifier: Framework :: Zope3
Classifier: Framework :: Plone
Classifier: Framework :: Plone :: 3.2
Classifier: Framework :: Plone :: 3.3
Classifier: Framework :: Plone :: 4.0
Classifier: Framework :: Plone :: 4.1
Classifier: Framework :: Plone :: 4.2
Classifier: Framework :: Plone :: 4.3
Classifier: Framework :: Buildout
Classifier: Intended Audience :: Developers
Classifier: License :: OSI Approved :: MIT License
Classifier: Programming Language :: Python
Classifier: Programming Language :: Python :: 2.4
Classifier: Programming Language :: Python :: 2.5
Classifier: Programming Language :: Python :: 2.6
Classifier: Programming Language :: Python :: 2.7
Classifier: Topic :: Software Development :: Code Generators
